[
  {
    "offset": 59302,
    "size": 55,
    "jpn": "劉備玄徳　義弟関羽、張飛と漢室再興を目指し、乱世に挑む_",
    "kor": "유비현덕　관우、장비와　한실재흥을　위해　난세에　도전"
  },
  {
    "offset": 59360,
    "size": 54,
    "jpn": "国都洛陽に君臨し、暴政の限りを尽くす、一世の梟雄　董卓",
    "kor": "국도　낙양에　군림、폭정을　펼치는　일세의　교웅　동탁"
  },
  {
    "offset": 59415,
    "size": 54,
    "jpn": "袁紹本初　華北を制し、一大勢力を狙う、名門袁家の御曹司",
    "kor": "원소본초　화북에　일대세력을　일군　명문　원가의　자제"
  },
  {
    "offset": 59470,
    "size": 54,
    "jpn": "江東の虎孫堅　その熱き野心は孫策、孫権へと受け継がれる",
    "kor": "강동의　손견　그의　야심은　손책、손권에게로　이어진다"
  },
  {
    "offset": 59525,
    "size": 54,
    "jpn": "曹操孟徳　中国制覇の野望に燃える、知勇兼備の乱世の姦雄",
    "kor": "조조맹덕　중국제패를　노리는、지용겸비의　난세의　간웅"
  },
  {
    "offset": 59626,
    "size": 26,
    "jpn": "歴史シミュレーションゲーム",
    "kor": "　역사　시뮬레이션　게임　"
  }
]